proxy_seller_user_api/__init__.py
proxy_seller_user_api-1.0.0.dist-info/LICENSE
proxy_seller_user_api-1.0.0.dist-info/METADATA
proxy_seller_user_api-1.0.0.dist-info/WHEEL
proxy_seller_user_api-1.0.0.dist-info/top_level.txt
proxy_seller_user_api-1.0.0.dist-info/RECORD
