Metadata-Version: 2.1
Name: proxy-seller-user-api
Version: 1.0.0
Summary: Interaction with user api
Home-page: https://bitbucket.org/proxy-seller/user-api-python
Author: proxy-seller
Author-email: support@proxy-seller.com
Project-URL: Documentation, https://proxy-seller.com/personal/api/
Keywords: api client
Classifier: Programming Language :: Python :: 3.11
Classifier: License :: OSI Approved :: MIT License
Classifier: Operating System :: OS Independent
Requires-Python: >=3.7
License-File: LICENSE
Requires-Dist: requests (>=2.25.1)
Requires-Dist: json
